blendedUx/__init__.py
blendedUx/blended_flask/__init__.py
blendedUx/blended_flask/app.py
blendedUx/blended_flask/bl_flask_app.py
blendedUx/blended_flask/functions.py
blendedUx/blended_flask/settings.py
blendedUx/blended_flask/utils.py
blendedUx/blended_flask/blended_hostlib/__init__.py
blendedUx/blended_flask/blended_hostlib/initializer.py
blendedUx/blended_flask/blended_hostlib/tests.py
blendedUx/blended_flask/blended_hostlib/transform_image.py
blendedUx/blended_flask/blended_hostlib/backend/__init__.py
blendedUx/blended_flask/blended_hostlib/backend/backend.py
blendedUx/blended_flask/blended_hostlib/backend/intermediary.py
blendedUx/blended_flask/blended_hostlib/backend/settings.py
blendedUx/blended_flask/blended_hostlib/controller/__init__.py
blendedUx/blended_flask/blended_hostlib/controller/controller.py
blendedUx/blended_flask/blended_hostlib/exceptions/__init__.py
blendedUx/blended_flask/blended_hostlib/exceptions/exceptions.py
blendedUx/blended_flask/blended_hostlib/functions/__init__.py
blendedUx/blended_flask/blended_hostlib/functions/functions.py
blendedUx/blended_flask/blended_hostlib/network/__init__.py
blendedUx/blended_flask/blended_hostlib/network/network.py
blendedUx/blended_flask/blended_hostlib/network/settings.py
blendedUx/blended_flask/blended_hostlib/swagger_client/__init__.py
blendedUx/blended_flask/blended_hostlib/swagger_client/api_client.py
blendedUx/blended_flask/blended_hostlib/swagger_client/configuration.py
blendedUx/blended_flask/blended_hostlib/swagger_client/rest.py
blendedUx/blended_flask/blended_hostlib/swagger_client/apis/__init__.py
blendedUx/blended_flask/blended_hostlib/swagger_client/apis/accounts_api.py
blendedUx/blended_flask/blended_hostlib/swagger_client/apis/packages_api.py
blendedUx/blended_flask/blended_hostlib/swagger_client/models/__init__.py
blendedUx/blended_flask/blended_hostlib/swagger_client/models/account.py
blendedUx/blended_flask/blended_hostlib/swagger_client/models/account_invite_pending.py
ux_graj-0.0.2.dist-info/LICENSE
ux_graj-0.0.2.dist-info/METADATA
ux_graj-0.0.2.dist-info/WHEEL
ux_graj-0.0.2.dist-info/top_level.txt
ux_graj-0.0.2.dist-info/RECORD
